Metadata-Version: 2.1
Name: odoo14-addon-account_banking_mandate_sale
Version: 14.0.1.0.1.dev12
Summary: Adds mandates on sale orders
Home-page: https://github.com/OCA/bank-payment
Author: Odoo Community Association (OCA), Akretion
Author-email: support@odoo-community.org
License: AGPL-3
Classifier: Programming Language :: Python
Classifier: Framework :: Odoo
Classifier: Framework :: Odoo :: 14.0
Classifier: License :: OSI Approved :: GNU Affero General Public License v3
Requires-Python: >=3.6
Requires-Dist: odoo14-addon-account-banking-mandate
Requires-Dist: odoo14-addon-account-payment-sale
Requires-Dist: odoo14-addon-sale-commercial-partner
Requires-Dist: odoo<14.1dev,>=14.0a
